README.md
src/pynx/__init__.py
src/pynx/__main__.py
src/pynx/pynx.py
src/pynx/util.py
pynx-0.1.0.dist-info/LICENSE
pynx-0.1.0.dist-info/WHEEL
pynx-0.1.0.dist-info/METADATA
pynx-0.1.0.dist-info/RECORD
