Metadata-Version: 2.1
Name: pynx
Version: 0.1.0
Summary: CLI tool for managing nginx daemon, sites and associated wsgi services
Home-page: https://pypi.org/project/pynx
License: MIT
Author: Timothy C. Quinn
Requires-Python: >=3.7.9,<4.0.0
Classifier: Development Status :: 3 - Alpha
Classifier: Environment :: Console
Classifier: Intended Audience :: System Administrators
Classifier: License :: OSI Approved :: MIT License
Classifier: Operating System :: MacOS :: MacOS X
Classifier: Operating System :: POSIX :: BSD
Classifier: Operating System :: POSIX :: Linux
Classifier: Operating System :: POSIX :: SunOS/Solaris
Classifier: Programming Language :: Python :: 3
Classifier: Programming Language :: Python :: 3 :: Only
Classifier: Programming Language :: Python :: 3.10
Classifier: Programming Language :: Python :: 3.7
Classifier: Programming Language :: Python :: 3.8
Classifier: Programming Language :: Python :: 3.9
Classifier: Topic :: System :: Systems Administration
Requires-Dist: gixy (>=0.1.20,<0.2.0)
Requires-Dist: texttable (>=1.6.3,<2.0.0)
Project-URL: Repository, https://github.com/JavaScriptDude/pynx
